test
inferno
