Metadata-Version: 1.0
Name: inferno
Version: 0.1.29
Summary: Inferno: a python map/reduce platform powered by disco.
Home-page: http://chango.com
Author: Chango Inc.
Author-email: dev@chango.com
License: MIT License
Keywords: inferno discoproject
Platform: UNKNOWN
